setup.py
TracFakeUsername.egg-info/PKG-INFO
TracFakeUsername.egg-info/SOURCES.txt
TracFakeUsername.egg-info/dependency_links.txt
TracFakeUsername.egg-info/entry_points.txt
TracFakeUsername.egg-info/top_level.txt
fakeusername/__init__.py
fakeusername/filter.py
fakeusername/htdocs/fakeusername.js
fakeusername/htdocs/jquery.js
