Metadata-Version: 1.0
Name: TracFakeUsername
Version: 1.0
Summary: Report tickets using a different name than that of the logged in user.
Home-page: http://trac-hacks.org/wiki/FakeUsernamePlugin
Author: Noah Kantrowitz
Author-email: coderanger@yahoo.com
License: BSD
Keywords: trac plugin ticket
Platform: UNKNOWN
Classifier: Framework :: Trac
